awsOnOff/__init__.py
awsOnOff/ec2.py
awsOnOff/ecs.py
awsOnOff/rds.py
awsOnOff-0.0.1.dist-info/LICENSE
awsOnOff-0.0.1.dist-info/METADATA
awsOnOff-0.0.1.dist-info/WHEEL
awsOnOff-0.0.1.dist-info/top_level.txt
awsOnOff-0.0.1.dist-info/RECORD
