Metadata-Version: 2.1
Name: awsOnOff
Version: 0.0.1
Summary: A python module for easily starting and stopping aws services(ec2 , ecs , rds)
Home-page: 
Author: Manish Kumar
Author-email: officialmanishkr98@gmail.com
License: GNU
Keywords: awsOnOff
Classifier: Development Status :: 5 - Production/Stable
Classifier: Intended Audience :: Education
Classifier: Operating System :: Microsoft :: Windows
Classifier: Operating System :: POSIX :: Linux
Classifier: Operating System :: MacOS :: MacOS X
Classifier: License :: OSI Approved :: GNU General Public License (GPL)
Classifier: Programming Language :: Python :: 3
License-File: LICENSE
Requires-Dist: boto3
Requires-Dist: PyYAML
